netlifyconfig/__init__.py
netlifyconfig/collection.py
netlifyconfig/netlify.py
netlifyconfig/py.typed
netlifyconfig/widgets.py
netlify_config_generator-0.1.2.dist-info/LICENSE
netlify_config_generator-0.1.2.dist-info/METADATA
netlify_config_generator-0.1.2.dist-info/WHEEL
netlify_config_generator-0.1.2.dist-info/top_level.txt
netlify_config_generator-0.1.2.dist-info/RECORD
