Metadata-Version: 2.1
Name: netlify-config-generator
Version: 0.1.2
Summary: Programatically generate netlify configuration files
Author: Nonowazu
Author-email: oowazu.nonowazu@gmail.com
License: MIT
Classifier: Programming Language :: Python :: 3 :: Only
Classifier: Programming Language :: Python :: 3.8
Classifier: Programming Language :: Python :: 3.9
Classifier: Programming Language :: Python :: 3.10
Requires-Python: >=3.8
License-File: LICENSE
Requires-Dist: pydantic <2.0,>=1.1
Provides-Extra: dev
Requires-Dist: mypy ==1.8.0 ; extra == 'dev'
Requires-Dist: pylint ==2.13.4 ; extra == 'dev'
Requires-Dist: coverage[toml] ==6.5.0 ; extra == 'dev'
Requires-Dist: black ==22.10.0 ; extra == 'dev'
